{
    "app_name": "default-model-app-intelliway",
    "gateway_ip": "http://localhost:",
    "port": 8080,
    "api_key": "3a6e920278777087ccbef399526f0a957f5e0236",
    "public_images": "/public/images/",
    "public_files": "/public/files/",
    "db_connection": "mongodb+srv://m001-student:m001-mongodb-basics@sandbox.twuyx.mongodb.net/myFirstDatabase?retryWrites=true&w=majority",
    "mail_host": "smtp.mailtrap.io",
    "mail_port": 2525,
    "mail_user": "504cbc11163b9c",
    "mail_password": "3423e8ba4a8080",
    "mail": "rhaymison.@hotmail.com",
    "s3_acess_key_id": "AKIAQVCBS4EZFYVRZGCJ",
    "s3_secret_acess_key": "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",
    "s3_bucket":"byio-cdn",
    "s3_general_path": "assets/"
}